Metadata-Version: 2.1
Name: teste-azure-ai-studio-001
Version: 0.0.1
Summary: This is my tools package
